python_app_boilerplate_25_d/__init__.py
python_app_boilerplate_25_d/example.py
python_app_boilerplate_25_d/main.py
python_app_boilerplate_25_d/resources/python-img.png
python_app_boilerplate_25_d-1.0.2.dist-info/METADATA
python_app_boilerplate_25_d-1.0.2.dist-info/WHEEL
python_app_boilerplate_25_d-1.0.2.dist-info/entry_points.txt
python_app_boilerplate_25_d-1.0.2.dist-info/licenses/LICENSE
python_app_boilerplate_25_d-1.0.2.dist-info/RECORD
