Metadata-Version: 2.4
Name: python-app-boilerplate-25-d
Version: 1.0.2
Summary: Simple Python Boilerplate
License-Expression: MIT
License-File: LICENSE
Requires-Python: >=3.12
Requires-Dist: pillow>=11.2.1
